{
  "deliveries": [
    {
      "id": 2,
      "title": "Entrega 2",
      "products": [
        {
          "id": 1,
          "name": "Kit Natura 1",
          "price": 79,
          "qnt": 1
        },
        {
          "id": 3,
          "name": "Sabonete Maracuj치",
          "price": 19,
          "qnt": 1
        },
        {
          "id": 4,
          "name": "Sabonete Menta",
          "price": 19,
          "qnt": 1
        }
      ],
      "client": {
        "id": 1,
        "name": "Camila Milaneze"
      },
      "isRead": false
    },
    {
      "id": 3,
      "title": "Entrega 3",
      "products": [
        {
          "id": 1,
          "name": "Kit Natura 1",
          "price": 79,
          "qnt": 1
        },
        {
          "id": 3,
          "name": "Sabonete Maracuj치",
          "price": 19,
          "qnt": 1
        }
      ],
      "client": {
        "id": 1,
        "name": "Eduardo Budny"
      },
      "isRead": false
    },
    {
      "id": 5,
      "title": "Entrega 5",
      "products": [
        {
          "id": 1,
          "name": "Kit Natura 1",
          "price": 79,
          "qnt": 1
        },
        {
          "id": 3,
          "name": "Sabonete Maracuj치",
          "price": 19,
          "qnt": 1
        }
      ],
      "client": {
        "id": 1,
        "name": "Eduardo Budny"
      },
      "isRead": false
    },
    {
      "id": 6,
      "title": "Entrega 6",
      "products": [
        {
          "id": 1,
          "name": "Kit Natura 1",
          "price": 79,
          "qnt": 1
        },
        {
          "id": 3,
          "name": "Sabonete Maracuj치",
          "price": 19,
          "qnt": 1
        }
      ],
      "client": {
        "id": 1,
        "name": "Eduardo Budny"
      },
      "isRead": false
    }
  ]
}